pyintellify.py
pyintellify-1.6.dist-info/COPYING.txt
pyintellify-1.6.dist-info/METADATA
pyintellify-1.6.dist-info/WHEEL
pyintellify-1.6.dist-info/top_level.txt
pyintellify-1.6.dist-info/RECORD
